apollo_py_numpy/__init__.py
apollo_py_numpy/robot_modules_runtime/__init__.py
apollo_py_numpy/robot_modules_runtime/urdf_numpy_module.py
apollo_py_numpy/spatial/__init__.py
apollo_py_numpy/spatial/isometries.py
apollo_py_numpy/spatial/lie/__init__.py
apollo_py_numpy/spatial/lie/h1.py
apollo_py_numpy/spatial/lie/se3_implicit.py
apollo_py_numpy/spatial/lie/se3_implicit_quaternion.py
apollo_py_numpy/spatial/lie/so3.py
apollo_py_numpy/spatial/matrices.py
apollo_py_numpy/spatial/quaternions.py
apollo_py_numpy/spatial/rotation_matrices.py
apollo_py_numpy/spatial/vectors.py
apollo_py_numpy-0.0.1.dist-info/LICENSE
apollo_py_numpy-0.0.1.dist-info/METADATA
apollo_py_numpy-0.0.1.dist-info/WHEEL
apollo_py_numpy-0.0.1.dist-info/RECORD
